pe/__init__.py
pe/app.py
pe/connect.py
pe/handler.py
pe/monitor.py
pe/tocsin.py
pyham_pe-1.1.1.dist-info/LICENSE
pyham_pe-1.1.1.dist-info/WHEEL
pyham_pe-1.1.1.dist-info/METADATA
pyham_pe-1.1.1.dist-info/RECORD
