Metadata-Version: 2.1
Name: pyham_pe
Version: 1.1.1
Summary: Packet Engine client for the AGWPE protocol
Keywords: ham radio,amateur radio,packet radio,AGWPE,protocol,connected mode,unproto
Author-email: Martin F N Cooper <mfncooper@gmail.com>
Requires-Python: >=3.7
Classifier: Development Status :: 5 - Production/Stable
Classifier: Intended Audience :: Developers
Classifier: License :: OSI Approved :: MIT License
Classifier: Programming Language :: Python :: 3 :: Only
Classifier: Topic :: Communications :: Ham Radio
Project-URL: Change Log, https://github.com/mfncooper/pyham_pe/blob/main/CHANGELOG.md
Project-URL: Documentation, https://pyham-pe.readthedocs.io
Project-URL: Source Code, https://github.com/mfncooper/pyham_pe
